aegis_memory/__init__.py
aegis_memory/client.py
aegis_memory/cli/__init__.py
aegis_memory/cli/main.py
aegis_memory/cli/commands/__init__.py
aegis_memory/cli/commands/config.py
aegis_memory/cli/commands/export_import.py
aegis_memory/cli/commands/features.py
aegis_memory/cli/commands/memory.py
aegis_memory/cli/commands/playbook.py
aegis_memory/cli/commands/progress.py
aegis_memory/cli/commands/stats.py
aegis_memory/cli/commands/status.py
aegis_memory/cli/commands/vote.py
aegis_memory/cli/utils/__init__.py
aegis_memory/cli/utils/auth.py
aegis_memory/cli/utils/config.py
aegis_memory/cli/utils/errors.py
aegis_memory/cli/utils/output.py
aegis_memory/integrations/__init__.py
aegis_memory/integrations/crewai.py
aegis_memory/integrations/langchain.py
aegis_memory-1.2.2.dist-info/METADATA
aegis_memory-1.2.2.dist-info/WHEEL
aegis_memory-1.2.2.dist-info/entry_points.txt
aegis_memory-1.2.2.dist-info/licenses/LICENSE
aegis_memory-1.2.2.dist-info/RECORD
