Metadata-Version: 2.4
Name: aegis-memory
Version: 1.2.2
Summary: Agent-native memory fabric for AI agents. Scoped, multi-agent, self-hosted.
Project-URL: Homepage, https://github.com/quantifylabs/aegis-memory
Project-URL: Documentation, https://github.com/quantifylabs/aegis-memory/tree/main/docs
Project-URL: Repository, https://github.com/quantifylabs/aegis-memory
Project-URL: Issues, https://github.com/quantifylabs/aegis-memory/issues
Project-URL: Changelog, https://github.com/quantifylabs/aegis-memory/blob/main/CHANGELOG.md
Author-email: Quantify Labs <arulnidhi@quantifylabs.ai>
License-Expression: Apache-2.0
License-File: LICENSE
Keywords: agents,ai,context-engineering,crewai,langchain,langgraph,llm,memory,multi-agent,pgvector,vector-database
Classifier: Development Status :: 4 - Beta
Classifier: Intended Audience :: Developers
Classifier: License :: OSI Approved :: Apache Software License
Classifier: Operating System :: OS Independent
Classifier: Programming Language :: Python :: 3
Classifier: Programming Language :: Python :: 3.10
Classifier: Programming Language :: Python :: 3.11
Classifier: Programming Language :: Python :: 3.12
Classifier: Topic :: Scientific/Engineering :: Artificial Intelligence
Classifier: Topic :: Software Development :: Libraries :: Python Modules
Requires-Python: >=3.10
Requires-Dist: httpx>=0.25.0
Requires-Dist: pyyaml>=6.0
Requires-Dist: rich>=13.0.0
Requires-Dist: typer[all]>=0.9.0
Provides-Extra: all
Requires-Dist: asyncpg>=0.29.0; extra == 'all'
Requires-Dist: crewai>=0.30.0; extra == 'all'
Requires-Dist: fastapi>=0.111.0; extra == 'all'
Requires-Dist: httpx>=0.25.0; extra == 'all'
Requires-Dist: langchain-core>=0.2.0; extra == 'all'
Requires-Dist: langchain>=0.2.0; extra == 'all'
Requires-Dist: mypy>=1.10.0; extra == 'all'
Requires-Dist: openai>=1.35.0; extra == 'all'
Requires-Dist: pgvector>=0.2.4; extra == 'all'
Requires-Dist: pydantic>=2.7.0; extra == 'all'
Requires-Dist: pytest-asyncio>=0.23.0; extra == 'all'
Requires-Dist: pytest-cov>=4.1.0; extra == 'all'
Requires-Dist: pytest>=8.0.0; extra == 'all'
Requires-Dist: ruff>=0.4.0; extra == 'all'
Requires-Dist: sqlalchemy[asyncio]>=2.0.25; extra == 'all'
Requires-Dist: uvicorn[standard]>=0.30.0; extra == 'all'
Provides-Extra: crewai
Requires-Dist: crewai>=0.30.0; extra == 'crewai'
Provides-Extra: dev
Requires-Dist: httpx>=0.25.0; extra == 'dev'
Requires-Dist: mypy>=1.10.0; extra == 'dev'
Requires-Dist: pytest-asyncio>=0.23.0; extra == 'dev'
Requires-Dist: pytest-cov>=4.1.0; extra == 'dev'
Requires-Dist: pytest>=8.0.0; extra == 'dev'
Requires-Dist: ruff>=0.4.0; extra == 'dev'
Provides-Extra: langchain
Requires-Dist: langchain-core>=0.2.0; extra == 'langchain'
Requires-Dist: langchain>=0.2.0; extra == 'langchain'
Provides-Extra: server
Requires-Dist: asyncpg>=0.29.0; extra == 'server'
Requires-Dist: fastapi>=0.111.0; extra == 'server'
Requires-Dist: openai>=1.35.0; extra == 'server'
Requires-Dist: pgvector>=0.2.4; extra == 'server'
Requires-Dist: pydantic>=2.7.0; extra == 'server'
Requires-Dist: sqlalchemy[asyncio]>=2.0.25; extra == 'server'
Requires-Dist: uvicorn[standard]>=0.30.0; extra == 'server'
